README.rst
setup.py
data_depgraph.egg-info/PKG-INFO
data_depgraph.egg-info/SOURCES.txt
data_depgraph.egg-info/dependency_links.txt
data_depgraph.egg-info/top_level.txt
depgraph/__init__.py
depgraph/buffer.py
depgraph/depgraph.py
tests/__init__.py
tests/buffer_tests.py
tests/depgraph_tests.py