Metadata-Version: 1.1
Name: data-depgraph
Version: 0.4.4
Summary: Micro dependency fulfillment library for scientific datasets
Home-page: https://github.com/njwilson23/depgraph
Author: Nat Wilson
Author-email: natw@fortyninemaps.com
License: MIT License
Platform: UNKNOWN
Classifier: Programming Language :: Python :: 2
Classifier: Programming Language :: Python :: 2.7
Classifier: Programming Language :: Python :: 3
Classifier: Programming Language :: Python :: 3.4
Classifier: Programming Language :: Python :: 3.5
Classifier: Programming Language :: Python :: 3.6
Classifier: License :: OSI Approved :: MIT License
